{
  "appId": "com.gestorativos.app",
  "appName": "Gestor de Ativos",
  "webDir": "www",
  "server": {
    "androidScheme": "https",
    "url": "https://meugestorativos.pages.dev/",
    "cleartext": true
  },
  "android": {
    "allowMixedContent": true,
    "webContentsDebuggingEnabled": true
  },
  "plugins": {
    "GoogleAuth": {
      "scopes": ["profile", "email"],
      "serverClientId": "384515121918-9e697a52b1647ed833bbaf.apps.googleusercontent.com",
      "forceCodeForRefreshToken": false
    }
  }
}
